conftest.py
dialoguekit/__init__.py
dialoguekit/connector/__init__.py
dialoguekit/connector/dialogue_connector.py
dialoguekit/core/__init__.py
dialoguekit/core/annotated_utterance.py
dialoguekit/core/annotation.py
dialoguekit/core/dialogue.py
dialoguekit/core/dialogue_act.py
dialoguekit/core/domain.py
dialoguekit/core/feedback.py
dialoguekit/core/intent.py
dialoguekit/core/slot_value_annotation.py
dialoguekit/core/utterance.py
dialoguekit/nlg/__init__.py
dialoguekit/nlg/nlg_abstract.py
dialoguekit/nlg/nlg_conditional.py
dialoguekit/nlg/nlg_template.py
dialoguekit/nlg/template_from_training_data.py
dialoguekit/nlg/models/LinearSVC_2_0.joblib
dialoguekit/nlg/models/vectorizer_0_0.joblib
dialoguekit/nlg/models/vectorizer_2_0.joblib
dialoguekit/nlu/__init__.py
dialoguekit/nlu/annotator.py
dialoguekit/nlu/dialogue_acts_extractor.py
dialoguekit/nlu/disjoint_dialogue_act_extractor.py
dialoguekit/nlu/intent_classifier.py
dialoguekit/nlu/nlu.py
dialoguekit/nlu/slot_annotator_dict.py
dialoguekit/nlu/slot_value_annotator.py
dialoguekit/nlu/models/__init__.py
dialoguekit/nlu/models/intent_classifier_cosine.py
dialoguekit/nlu/models/satisfaction_classifier.py
dialoguekit/nlu/models/satisfaction/LinearSVC_2_0.joblib
dialoguekit/nlu/models/satisfaction/__init__.py
dialoguekit/nlu/models/satisfaction/vectorizer_0_0.joblib
dialoguekit/nlu/models/satisfaction/vectorizer_2_0.joblib
dialoguekit/participant/__init__.py
dialoguekit/participant/agent.py
dialoguekit/participant/participant.py
dialoguekit/participant/user.py
dialoguekit/participant/user_preferences.py
dialoguekit/platforms/__init__.py
dialoguekit/platforms/flask_socket_platform.py
dialoguekit/platforms/platform.py
dialoguekit/platforms/terminal_platform.py
dialoguekit/utils/__init__.py
dialoguekit/utils/annotation_converter.py
dialoguekit/utils/dialogue_evaluation.py
dialoguekit/utils/dialogue_reader.py
dialoguekit-0.1.1.dist-info/licenses/LICENSE
docs/source/conf.py
sample_agents/__init__.py
sample_agents/moviebot_agent.py
sample_agents/parrot_agent.py
dialoguekit-0.1.1.dist-info/METADATA
dialoguekit-0.1.1.dist-info/WHEEL
dialoguekit-0.1.1.dist-info/top_level.txt
dialoguekit-0.1.1.dist-info/RECORD
