Metadata-Version: 2.4
Name: dialoguekit
Version: 0.1.1
Summary: Toolkit for building conversational information access systems.
Author: Nolwenn Bernard, Krisztian Balog, Jafar Afzali, Aleksander Drzewiecki, Shuo Zhang
Project-URL: Repository, https://github.com/iai-group/dialoguekit
Project-URL: Issues, https://github.com/iai-group/dialoguekit/issues
Classifier: Programming Language :: Python :: 3
Classifier: License :: OSI Approved :: Apache Software License
Classifier: Operating System :: OS Independent
Requires-Python: >=3.11
License-File: LICENSE
Requires-Dist: Flask>=2.3.2
Requires-Dist: flask-socketio>=5.3.3
Requires-Dist: Werkzeug>=2.3.3
Requires-Dist: websockets<11.0
Requires-Dist: requests>=2.32.5
Requires-Dist: pyyaml>=6.0
Dynamic: license-file
